AtomicContributions/ContributionsOfAtomsToModes.py
AtomicContributions/__init__.py
AtomicContributions_JaGeo-1.5.0.dist-info/LICENSE
AtomicContributions_JaGeo-1.5.0.dist-info/METADATA
AtomicContributions_JaGeo-1.5.0.dist-info/WHEEL
AtomicContributions_JaGeo-1.5.0.dist-info/top_level.txt
AtomicContributions_JaGeo-1.5.0.dist-info/RECORD
