Metadata-Version: 2.1
Name: AtomicContributions-JaGeo
Version: 1.5.0
Summary: Package to display atomic contributions to modes
Home-page: https://github.com/JaGeo/AtomicContributions
Author: Janine George
Author-email: janine.george@uclouvain.be
License: UNKNOWN
Platform: UNKNOWN
Classifier: Programming Language :: Python :: 3
Classifier: License :: OSI Approved :: BSD License
Classifier: Operating System :: OS Independent
Requires-Dist: numpy (>=1.14.3)
Requires-Dist: phonopy (>=2.1.1)
Requires-Dist: matplotlib (>=3.0.2)
